{
  "nodes": {
    "N064": {
      "x": 2373.0,
      "y": 1161.0,
      "name": "ห้องปฏิบัติการทางสิ่งแวดล้อม",
      "type": "room",
      "floor": 4
    },
    "N065": {
      "x": 2307.0,
      "y": 1068.0,
      "name": "ห้องAnimal Lab",
      "type": "room",
      "floor": 4
    },
    "N066": {
      "x": 2307.0,
      "y": 993.0,
      "name": "ห้องเก็บสารเคมี",
      "type": "room",
      "floor": 4
    },
    "N067": {
      "x": 2323.0,
      "y": 911.0,
      "name": "ห้องปฏิบัติการกลาง 2409",
      "type": "room",
      "floor": 4
    },
    "N068": {
      "x": 2373.0,
      "y": 818.0,
      "name": "ห้องปฏิบัติการPollen 2408",
      "type": "room",
      "floor": 4
    },
    "N069": {
      "x": 2382.0,
      "y": 680.0,
      "name": "ห้องปฏิบัติการPollen 2407",
      "type": "room",
      "floor": 4
    },
    "N070": {
      "x": 1998.0,
      "y": 946.0,
      "name": "ห้องปฏิบัติการเทคโนโลยีชีวภาพ 2405",
      "type": "room",
      "floor": 4
    },
    "N071": {
      "x": 2073.0,
      "y": 1055.0,
      "name": "ห้องเตรียมปฏิบัติการ 2405",
      "type": "room",
      "floor": 4
    },
    "N072": {
      "x": 2004.0,
      "y": 730.0,
      "name": "ห้องปฏิบัติการสัตววิทยา 2406",
      "type": "room",
      "floor": 4
    },
    "N073": {
      "x": 1751.0,
      "y": 793.0,
      "name": "ห้องปฏิบัติการชีววิทยา 2404",
      "type": "room",
      "floor": 4
    },
    "N074": {
      "x": 1701.0,
      "y": 1074.0,
      "name": "ห้องพักอาจารย์ 2404",
      "type": "room",
      "floor": 4
    },
    "N075": {
      "x": 1497.0,
      "y": 968.0,
      "name": "ห้องสัมนา 2402",
      "type": "room",
      "floor": 4
    },
    "N076": {
      "x": 1497.0,
      "y": 730.0,
      "name": "ห้อง Posthavest 2403",
      "type": "room",
      "floor": 4
    },
    "N077": {
      "x": 1444.0,
      "y": 605.0,
      "name": "ห้องเตรียมปฏิบัติการ 2403",
      "type": "room",
      "floor": 4
    },
    "N078": {
      "x": 2063.0,
      "y": 602.0,
      "name": "ห้องอณูชีววิทยา 2406",
      "type": "room",
      "floor": 4
    },
    "N079": {
      "x": 1929.0,
      "y": 1255.0,
      "name": "ห้องน้ำหญิง",
      "type": "room",
      "floor": 4
    },
    "N080": {
      "x": 1579.0,
      "y": 1258.0,
      "name": "ห้องน้ำชาย",
      "type": "room",
      "floor": 4
    },
    "N081": {
      "x": 1441.0,
      "y": 1261.0,
      "name": "ลิฟท์ ชั้น4",
      "type": "elevator",
      "floor": 4
    },
    "N082": {
      "x": 1197.0,
      "y": 1055.0,
      "name": "ห้องสำนักงาน 2401",
      "type": "room",
      "floor": 4
    },
    "N083": {
      "x": 1060.0,
      "y": 1505.0,
      "name": "โซนเตรียมอาหาร",
      "type": "room",
      "floor": 4
    },
    "N084": {
      "x": 1210.0,
      "y": 1496.0,
      "name": "ห้องถ่ายเนื้อเยื้อ",
      "type": "room",
      "floor": 4
    },
    "N085": {
      "x": 1166.0,
      "y": 1324.0,
      "name": "ห้องสำนักงานเพาะเลี้ยงเนื้อเยื้อ",
      "type": "room",
      "floor": 4
    },
    "N086": {
      "x": 1035.0,
      "y": 1380.0,
      "name": "ห้องเตรียมปฏิบัติการ",
      "type": "room",
      "floor": 4
    },
    "N087": {
      "x": 1038.0,
      "y": 1652.0,
      "name": "ห้องเก็บของ",
      "type": "room",
      "floor": 4
    },
    "N088": {
      "x": 1204.0,
      "y": 1733.0,
      "name": "ห้องเก็บของ",
      "type": "room",
      "floor": 4
    },
    "N089": {
      "x": 1510.0,
      "y": 1336.0,
      "name": "ห้องปฏิบัติการสิ่งแวดล้อมและจุลชีววิทยา",
      "type": "room",
      "floor": 4
    },
    "N090": {
      "x": 1460.0,
      "y": 1471.0,
      "name": "ห้องประชุมสาขาวิชา",
      "type": "room",
      "floor": 4
    },
    "N091": {
      "x": 1444.0,
      "y": 1521.0,
      "name": "ห้องคอมพิวเตอร์",
      "type": "room",
      "floor": 4
    },
    "N092": {
      "x": 1588.0,
      "y": 1505.0,
      "name": "ห้องบรรยาย ป.โท",
      "type": "room",
      "floor": 4
    },
    "N093": {
      "x": 1488.0,
      "y": 1661.0,
      "name": "Room N093",
      "type": "room",
      "floor": 4
    },
    "N094": {
      "x": 1648.0,
      "y": 1686.0,
      "name": "ห้องเตรียมปฏิบัติการ",
      "type": "room",
      "floor": 4
    },
    "N095": {
      "x": 2066.0,
      "y": 1255.0,
      "name": "บันไดกลาง",
      "type": "stair",
      "floor": 4
    },
    "N096": {
      "x": 2191.0,
      "y": 618.0,
      "name": "บันไดขวา",
      "type": "stair",
      "floor": 4
    },
    "N097": {
      "x": 1322.0,
      "y": 686.0,
      "name": "บันไดซ้าย",
      "type": "stair",
      "floor": 4
    },
    "N098": {
      "x": 2241.0,
      "y": 1161.0,
      "name": "Door N098",
      "type": "door",
      "floor": 4
    },
    "N099": {
      "x": 2235.0,
      "y": 908.0,
      "name": "Door N099",
      "type": "door",
      "floor": 4
    },
    "N100": {
      "x": 2382.0,
      "y": 964.0,
      "name": "Door N100",
      "type": "door",
      "floor": 4
    },
    "N101": {
      "x": 2435.0,
      "y": 964.0,
      "name": "Door N101",
      "type": "door",
      "floor": 4
    },
    "N102": {
      "x": 2432.0,
      "y": 930.0,
      "name": "Door N102",
      "type": "door",
      "floor": 4
    },
    "N103": {
      "x": 2382.0,
      "y": 1043.0,
      "name": "Door N103",
      "type": "door",
      "floor": 4
    },
    "N104": {
      "x": 2429.0,
      "y": 1043.0,
      "name": "Door N104",
      "type": "door",
      "floor": 4
    },
    "N105": {
      "x": 2148.0,
      "y": 868.0,
      "name": "Door N105",
      "type": "door",
      "floor": 4
    },
    "N106": {
      "x": 2148.0,
      "y": 799.0,
      "name": "Door N106",
      "type": "door",
      "floor": 4
    },
    "N107": {
      "x": 2129.0,
      "y": 1024.0,
      "name": "Door N107",
      "type": "door",
      "floor": 4
    },
    "N108": {
      "x": 1866.0,
      "y": 858.0,
      "name": "Door N108",
      "type": "door",
      "floor": 4
    },
    "N109": {
      "x": 1863.0,
      "y": 811.0,
      "name": "Door N109",
      "type": "door",
      "floor": 4
    },
    "N110": {
      "x": 1635.0,
      "y": 814.0,
      "name": "Door N110",
      "type": "door",
      "floor": 4
    },
    "N111": {
      "x": 1632.0,
      "y": 855.0,
      "name": "Door N111",
      "type": "door",
      "floor": 4
    },
    "N112": {
      "x": 1776.0,
      "y": 1036.0,
      "name": "Door N112",
      "type": "door",
      "floor": 4
    },
    "N113": {
      "x": 1823.0,
      "y": 1021.0,
      "name": "Door N113",
      "type": "door",
      "floor": 4
    },
    "N114": {
      "x": 1813.0,
      "y": 1114.0,
      "name": "Door N114",
      "type": "door",
      "floor": 4
    },
    "N115": {
      "x": 1363.0,
      "y": 1077.0,
      "name": "Door N115",
      "type": "door",
      "floor": 4
    },
    "N116": {
      "x": 1372.0,
      "y": 871.0,
      "name": "Door N116",
      "type": "door",
      "floor": 4
    },
    "N117": {
      "x": 1372.0,
      "y": 799.0,
      "name": "Door N117",
      "type": "door",
      "floor": 4
    },
    "N118": {
      "x": 1322.0,
      "y": 1211.0,
      "name": "Door N118",
      "type": "door",
      "floor": 4
    },
    "N119": {
      "x": 1116.0,
      "y": 1114.0,
      "name": "Door N119",
      "type": "door",
      "floor": 4
    },
    "N120": {
      "x": 1272.0,
      "y": 1161.0,
      "name": "Door N120",
      "type": "door",
      "floor": 4
    },
    "N121": {
      "x": 1129.0,
      "y": 1293.0,
      "name": "Door N121",
      "type": "door",
      "floor": 4
    },
    "N122": {
      "x": 1072.0,
      "y": 1418.0,
      "name": "Door N122",
      "type": "door",
      "floor": 4
    },
    "N123": {
      "x": 1141.0,
      "y": 1424.0,
      "name": "Door N123",
      "type": "door",
      "floor": 4
    },
    "N124": {
      "x": 1135.0,
      "y": 1380.0,
      "name": "Door N124",
      "type": "door",
      "floor": 4
    },
    "N125": {
      "x": 1082.0,
      "y": 1611.0,
      "name": "Door N125",
      "type": "door",
      "floor": 4
    },
    "N126": {
      "x": 1129.0,
      "y": 1718.0,
      "name": "Door N126",
      "type": "door",
      "floor": 4
    },
    "N127": {
      "x": 1144.0,
      "y": 1568.0,
      "name": "Door N127",
      "type": "door",
      "floor": 4
    },
    "N128": {
      "x": 1147.0,
      "y": 1633.0,
      "name": "Door N128",
      "type": "door",
      "floor": 4
    },
    "N129": {
      "x": 1201.0,
      "y": 1671.0,
      "name": "ห้องเลี้ยงต้นไม้",
      "type": "room",
      "floor": 4
    },
    "N130": {
      "x": 2019.0,
      "y": 1218.0,
      "name": "Door N130",
      "type": "door",
      "floor": 4
    },
    "N131": {
      "x": 1985.0,
      "y": 1214.0,
      "name": "Door N131",
      "type": "door",
      "floor": 4
    },
    "N132": {
      "x": 1526.0,
      "y": 1218.0,
      "name": "Door N132",
      "type": "door",
      "floor": 4
    },
    "N133": {
      "x": 1441.0,
      "y": 1214.0,
      "name": "Door N133",
      "type": "door",
      "floor": 4
    },
    "N134": {
      "x": 2132.0,
      "y": 649.0,
      "name": "Door N134",
      "type": "door",
      "floor": 4
    },
    "N135": {
      "x": 1376.0,
      "y": 649.0,
      "name": "Door N135",
      "type": "door",
      "floor": 4
    },
    "N136": {
      "x": 1366.0,
      "y": 1577.0,
      "name": "Door N136",
      "type": "door",
      "floor": 4
    },
    "N137": {
      "x": 1372.0,
      "y": 1468.0,
      "name": "Door N137",
      "type": "door",
      "floor": 4
    },
    "N138": {
      "x": 1391.0,
      "y": 1452.0,
      "name": "Door N138",
      "type": "door",
      "floor": 4
    },
    "N139": {
      "x": 1388.0,
      "y": 1486.0,
      "name": "Door N139",
      "type": "door",
      "floor": 4
    },
    "N140": {
      "x": 1369.0,
      "y": 1324.0,
      "name": "Door N140",
      "type": "door",
      "floor": 4
    },
    "N141": {
      "x": 1626.0,
      "y": 1618.0,
      "name": "Door N141",
      "type": "door",
      "floor": 4
    },
    "N142": {
      "x": 2235.0,
      "y": 818.0,
      "name": "Door N142",
      "type": "door",
      "floor": 4
    },
    "N143": {
      "x": 2232.0,
      "y": 736.0,
      "name": "Door N143",
      "type": "door",
      "floor": 4
    }
  }
}